mastercard_spendalerts-1.0.6.dist-info/DESCRIPTION.rst
mastercard_spendalerts-1.0.6.dist-info/METADATA
mastercard_spendalerts-1.0.6.dist-info/RECORD
mastercard_spendalerts-1.0.6.dist-info/WHEEL
mastercard_spendalerts-1.0.6.dist-info/metadata.json
mastercard_spendalerts-1.0.6.dist-info/top_level.txt
mastercardspendalerts/__init__.py
mastercardspendalerts/alerts.py
mastercardspendalerts/amount.py
mastercardspendalerts/batch.py
mastercardspendalerts/card.py
mastercardspendalerts/channel.py
mastercardspendalerts/controls.py
mastercardspendalerts/controlshistory.py
mastercardspendalerts/crossborder.py
mastercardspendalerts/declineall.py
mastercardspendalerts/declines.py
mastercardspendalerts/notification.py
mastercardspendalerts/resourceconfig.py
mastercardspendalerts/txnhistory.py
mastercardspendalerts/verify.py
